rocketrag/__init__.py
rocketrag/__main__.py
rocketrag/base.py
rocketrag/chonk.py
rocketrag/cli.py
rocketrag/data_models.py
rocketrag/db.py
rocketrag/display_utils.py
rocketrag/llm.py
rocketrag/loaders.py
rocketrag/rag.py
rocketrag/rocketrag.py
rocketrag/utils.py
rocketrag/vectors.py
rocketrag/visualization.py
rocketrag/webserver/__init__.py
rocketrag/webserver/models.py
rocketrag/webserver/routes.py
rocketrag/webserver/templates/base.html
rocketrag/webserver/templates/browse.html
rocketrag/webserver/templates/chat.html
rocketrag/webserver/templates/index.html
rocketrag/webserver/templates/visualize.html
rocketrag-0.1.5.dist-info/licenses/LICENSE
rocketrag-0.1.5.dist-info/METADATA
rocketrag-0.1.5.dist-info/WHEEL
rocketrag-0.1.5.dist-info/entry_points.txt
rocketrag-0.1.5.dist-info/top_level.txt
rocketrag-0.1.5.dist-info/RECORD
