Metadata-Version: 2.4
Name: rocketrag
Version: 0.1.5
Summary: Fast, efficient, minimal, extendible and elegant RAG system
Author-email: Aleksander Obuchowski <obuchowskialeksander@gmail.com>
License: CC-BY-4.0
Project-URL: Homepage, https://github.com/TheLion-ai/RocketRAG
Project-URL: Repository, https://github.com/TheLion-ai/RocketRAG
Project-URL: Documentation, https://github.com/TheLion-ai/RocketRAG#readme
Project-URL: Bug Tracker, https://github.com/TheLion-ai/RocketRAG/issues
Keywords: rag,retrieval,llm,ai,vector-database,embeddings
Classifier: Development Status :: 3 - Alpha
Classifier: Intended Audience :: Developers
Classifier: Programming Language :: Python :: 3
Classifier: Programming Language :: Python :: 3.12
Classifier: Topic :: Scientific/Engineering :: Artificial Intelligence
Classifier: Topic :: Software Development :: Libraries :: Python Modules
Requires-Python: >=3.12
License-File: LICENSE
Requires-Dist: chonkie[model2vec]>=1.1.2
Requires-Dist: fastapi>=0.116.1
Requires-Dist: jinja2>=3.1.0
Requires-Dist: kreuzberg>=3.11.2
Requires-Dist: llama-cpp-python>=0.3.16
Requires-Dist: numpy>=1.24.0
Requires-Dist: pymilvus>=2.6.0
Requires-Dist: rich>=13.0.0
Requires-Dist: sentence-transformers>=5.1.0
Requires-Dist: typer>=0.16.1
Requires-Dist: uvicorn>=0.32.1
Provides-Extra: dev
Requires-Dist: pytest>=8.0.0; extra == "dev"
Requires-Dist: pytest-cov>=6.0.0; extra == "dev"
Requires-Dist: ruff>=0.8.0; extra == "dev"
Provides-Extra: viz
Requires-Dist: scikit-learn>=1.3.0; extra == "viz"
Dynamic: license-file
